geochemdb/__init__.py
geochemdb/geochemdb.py
geochemdb-1.1.1.dist-info/licenses/LICENSE.txt
geochemdb-1.1.1.dist-info/METADATA
geochemdb-1.1.1.dist-info/WHEEL
geochemdb-1.1.1.dist-info/top_level.txt
geochemdb-1.1.1.dist-info/RECORD
